{
    "class_id": 0,
    "bbox": {
        "center_x": 0.5066964285714286,
        "center_y": 0.44419642857142855,
        "width": 0.4955357142857143,
        "height": 0.8883928571428571
    },
    "keypoints": {
        "wrist": {
            "x": 0.39878013730049133,
            "y": 0.8445498943328857,
            "v": 2.0
        },
        "thumb_cmc": {
            "x": 0.5370786786079407,
            "y": 0.8058846592903137,
            "v": 2.0
        },
        "thumb_mcp": {
            "x": 0.6287667155265808,
            "y": 0.6728187203407288,
            "v": 2.0
        },
        "thumb_ip": {
            "x": 0.6633810997009277,
            "y": 0.5382534861564636,
            "v": 2.0
        },
        "thumb_tip": {
            "x": 0.7133647203445435,
            "y": 0.44381463527679443,
            "v": 2.0
        },
        "index_mcp": {
            "x": 0.5619772672653198,
            "y": 0.4629221558570862,
            "v": 2.0
        },
        "index_pip": {
            "x": 0.579099178314209,
            "y": 0.2935025990009308,
            "v": 2.0
        },
        "index_dip": {
            "x": 0.5721856951713562,
            "y": 0.18902777135372162,
            "v": 2.0
        },
        "index_tip": {
            "x": 0.5576417446136475,
            "y": 0.09860378503799438,
            "v": 2.0
        },
        "middle_mcp": {
            "x": 0.4714476466178894,
            "y": 0.43874025344848633,
            "v": 2.0
        },
        "middle_pip": {
            "x": 0.48523271083831787,
            "y": 0.25093162059783936,
            "v": 2.0
        },
        "middle_dip": {
            "x": 0.4840162992477417,
            "y": 0.12823083996772766,
            "v": 2.0
        },
        "middle_tip": {
            "x": 0.478287011384964,
            "y": 0.027792274951934814,
            "v": 2.0
        },
        "ring_mcp": {
            "x": 0.3890235424041748,
            "y": 0.4489908218383789,
            "v": 2.0
        },
        "ring_pip": {
            "x": 0.39655470848083496,
            "y": 0.2753313183784485,
            "v": 2.0
        },
        "ring_dip": {
            "x": 0.4085421860218048,
            "y": 0.16748012602329254,
            "v": 2.0
        },
        "ring_tip": {
            "x": 0.41917750239372253,
            "y": 0.0759858787059784,
            "v": 2.0
        },
        "pinky_mcp": {
            "x": 0.305519163608551,
            "y": 0.48833227157592773,
            "v": 2.0
        },
        "pinky_pip": {
            "x": 0.30400246381759644,
            "y": 0.35420918464660645,
            "v": 2.0
        },
        "pinky_dip": {
            "x": 0.310526579618454,
            "y": 0.2681019902229309,
            "v": 2.0
        },
        "pinky_tip": {
            "x": 0.32007384300231934,
            "y": 0.18816599249839783,
            "v": 2.0
        }
    }
}