{
    "class_id": 0,
    "bbox": {
        "center_x": 0.5290178571428571,
        "center_y": 0.578125,
        "width": 0.20089285714285715,
        "height": 0.4419642857142857
    },
    "keypoints": {
        "wrist": {
            "x": 0.5280022025108337,
            "y": 0.7558339238166809,
            "v": 2.0
        },
        "thumb_cmc": {
            "x": 0.48234689235687256,
            "y": 0.6958955526351929,
            "v": 2.0
        },
        "thumb_mcp": {
            "x": 0.474187433719635,
            "y": 0.6208757758140564,
            "v": 2.0
        },
        "thumb_ip": {
            "x": 0.48717039823532104,
            "y": 0.5687761306762695,
            "v": 2.0
        },
        "thumb_tip": {
            "x": 0.5048240423202515,
            "y": 0.534912109375,
            "v": 2.0
        },
        "index_mcp": {
            "x": 0.536663830280304,
            "y": 0.5775308609008789,
            "v": 2.0
        },
        "index_pip": {
            "x": 0.5537318587303162,
            "y": 0.5112954378128052,
            "v": 2.0
        },
        "index_dip": {
            "x": 0.5626934766769409,
            "y": 0.4636053442955017,
            "v": 2.0
        },
        "index_tip": {
            "x": 0.569365918636322,
            "y": 0.42238178849220276,
            "v": 2.0
        },
        "middle_mcp": {
            "x": 0.5572680234909058,
            "y": 0.5836004614830017,
            "v": 2.0
        },
        "middle_pip": {
            "x": 0.5715368390083313,
            "y": 0.5113189220428467,
            "v": 2.0
        },
        "middle_dip": {
            "x": 0.5769102573394775,
            "y": 0.4558829367160797,
            "v": 2.0
        },
        "middle_tip": {
            "x": 0.5786588191986084,
            "y": 0.40590521693229675,
            "v": 2.0
        },
        "ring_mcp": {
            "x": 0.5697759985923767,
            "y": 0.5993977785110474,
            "v": 2.0
        },
        "ring_pip": {
            "x": 0.5795795321464539,
            "y": 0.5344114899635315,
            "v": 2.0
        },
        "ring_dip": {
            "x": 0.584201991558075,
            "y": 0.48553889989852905,
            "v": 2.0
        },
        "ring_tip": {
            "x": 0.5864320993423462,
            "y": 0.44052964448928833,
            "v": 2.0
        },
        "pinky_mcp": {
            "x": 0.5748810768127441,
            "y": 0.6227808594703674,
            "v": 2.0
        },
        "pinky_pip": {
            "x": 0.5764710307121277,
            "y": 0.5722277164459229,
            "v": 2.0
        },
        "pinky_dip": {
            "x": 0.5774371027946472,
            "y": 0.537027895450592,
            "v": 2.0
        },
        "pinky_tip": {
            "x": 0.5776129961013794,
            "y": 0.5064762234687805,
            "v": 2.0
        }
    }
}