{
    "class_id": 0,
    "bbox": {
        "center_x": 0.3549107142857143,
        "center_y": 0.48660714285714285,
        "width": 0.4955357142857143,
        "height": 0.9107142857142857
    },
    "keypoints": {
        "wrist": {
            "x": 0.38417282700538635,
            "y": 0.07863008975982666,
            "v": 2.0
        },
        "thumb_cmc": {
            "x": 0.515413761138916,
            "y": 0.17484822869300842,
            "v": 2.0
        },
        "thumb_mcp": {
            "x": 0.5596905946731567,
            "y": 0.32965537905693054,
            "v": 2.0
        },
        "thumb_ip": {
            "x": 0.5326164960861206,
            "y": 0.46555739641189575,
            "v": 2.0
        },
        "thumb_tip": {
            "x": 0.5412993431091309,
            "y": 0.5851619243621826,
            "v": 2.0
        },
        "index_mcp": {
            "x": 0.4303716719150543,
            "y": 0.49856051802635193,
            "v": 2.0
        },
        "index_pip": {
            "x": 0.39861345291137695,
            "y": 0.6650635004043579,
            "v": 2.0
        },
        "index_dip": {
            "x": 0.36911866068840027,
            "y": 0.7711002826690674,
            "v": 2.0
        },
        "index_tip": {
            "x": 0.33783939480781555,
            "y": 0.8637149333953857,
            "v": 2.0
        },
        "middle_mcp": {
            "x": 0.3461427092552185,
            "y": 0.4912795126438141,
            "v": 2.0
        },
        "middle_pip": {
            "x": 0.3088710904121399,
            "y": 0.6754191517829895,
            "v": 2.0
        },
        "middle_dip": {
            "x": 0.2785532474517822,
            "y": 0.7971463203430176,
            "v": 2.0
        },
        "middle_tip": {
            "x": 0.25011277198791504,
            "y": 0.9014446139335632,
            "v": 2.0
        },
        "ring_mcp": {
            "x": 0.27773743867874146,
            "y": 0.4514642059803009,
            "v": 2.0
        },
        "ring_pip": {
            "x": 0.24125227332115173,
            "y": 0.623744785785675,
            "v": 2.0
        },
        "ring_dip": {
            "x": 0.21804383397102356,
            "y": 0.7334496974945068,
            "v": 2.0
        },
        "ring_tip": {
            "x": 0.1980326622724533,
            "y": 0.8265925645828247,
            "v": 2.0
        },
        "pinky_mcp": {
            "x": 0.2100304216146469,
            "y": 0.38454073667526245,
            "v": 2.0
        },
        "pinky_pip": {
            "x": 0.1760491281747818,
            "y": 0.5225884914398193,
            "v": 2.0
        },
        "pinky_dip": {
            "x": 0.16135239601135254,
            "y": 0.6124066710472107,
            "v": 2.0
        },
        "pinky_tip": {
            "x": 0.15456831455230713,
            "y": 0.6930541396141052,
            "v": 2.0
        }
    }
}