{
    "class_id": 0,
    "bbox": {
        "center_x": 0.48660714285714285,
        "center_y": 0.4642857142857143,
        "width": 0.6875,
        "height": 0.9285714285714286
    },
    "keypoints": {
        "wrist": {
            "x": 0.49410033226013184,
            "y": 0.045934200286865234,
            "v": 2.0
        },
        "thumb_cmc": {
            "x": 0.6329798698425293,
            "y": 0.14895403385162354,
            "v": 2.0
        },
        "thumb_mcp": {
            "x": 0.710235595703125,
            "y": 0.30711039900779724,
            "v": 2.0
        },
        "thumb_ip": {
            "x": 0.7415391206741333,
            "y": 0.44231829047203064,
            "v": 2.0
        },
        "thumb_tip": {
            "x": 0.7862488031387329,
            "y": 0.5539696216583252,
            "v": 2.0
        },
        "index_mcp": {
            "x": 0.5042994618415833,
            "y": 0.5112782716751099,
            "v": 2.0
        },
        "index_pip": {
            "x": 0.4671992361545563,
            "y": 0.6753032803535461,
            "v": 2.0
        },
        "index_dip": {
            "x": 0.4411458671092987,
            "y": 0.7745020389556885,
            "v": 2.0
        },
        "index_tip": {
            "x": 0.41490182280540466,
            "y": 0.8601036071777344,
            "v": 2.0
        },
        "middle_mcp": {
            "x": 0.4057226777076721,
            "y": 0.5029855370521545,
            "v": 2.0
        },
        "middle_pip": {
            "x": 0.36522597074508667,
            "y": 0.6825530529022217,
            "v": 2.0
        },
        "middle_dip": {
            "x": 0.3406095504760742,
            "y": 0.7935294508934021,
            "v": 2.0
        },
        "middle_tip": {
            "x": 0.32176700234413147,
            "y": 0.886175274848938,
            "v": 2.0
        },
        "ring_mcp": {
            "x": 0.32591718435287476,
            "y": 0.4648679792881012,
            "v": 2.0
        },
        "ring_pip": {
            "x": 0.27912819385528564,
            "y": 0.6355763077735901,
            "v": 2.0
        },
        "ring_dip": {
            "x": 0.25957736372947693,
            "y": 0.7432259917259216,
            "v": 2.0
        },
        "ring_tip": {
            "x": 0.24843063950538635,
            "y": 0.833827018737793,
            "v": 2.0
        },
        "pinky_mcp": {
            "x": 0.25295040011405945,
            "y": 0.3997206687927246,
            "v": 2.0
        },
        "pinky_pip": {
            "x": 0.2048097550868988,
            "y": 0.5361913442611694,
            "v": 2.0
        },
        "pinky_dip": {
            "x": 0.19009608030319214,
            "y": 0.6257166862487793,
            "v": 2.0
        },
        "pinky_tip": {
            "x": 0.1877690851688385,
            "y": 0.7051018476486206,
            "v": 2.0
        }
    }
}