{
    "class_id": 0,
    "bbox": {
        "center_x": 0.5044642857142857,
        "center_y": 0.5647321428571429,
        "width": 0.2767857142857143,
        "height": 0.47767857142857145
    },
    "keypoints": {
        "wrist": {
            "x": 0.4516585171222687,
            "y": 0.7626487612724304,
            "v": 2.0
        },
        "thumb_cmc": {
            "x": 0.5087190270423889,
            "y": 0.7545335292816162,
            "v": 2.0
        },
        "thumb_mcp": {
            "x": 0.5501160621643066,
            "y": 0.7031161189079285,
            "v": 2.0
        },
        "thumb_ip": {
            "x": 0.5719889402389526,
            "y": 0.6570792198181152,
            "v": 2.0
        },
        "thumb_tip": {
            "x": 0.6003667116165161,
            "y": 0.6340191960334778,
            "v": 2.0
        },
        "index_mcp": {
            "x": 0.5089759826660156,
            "y": 0.5784740447998047,
            "v": 2.0
        },
        "index_pip": {
            "x": 0.5089024901390076,
            "y": 0.5007649660110474,
            "v": 2.0
        },
        "index_dip": {
            "x": 0.5057838559150696,
            "y": 0.4493584632873535,
            "v": 2.0
        },
        "index_tip": {
            "x": 0.5007935166358948,
            "y": 0.40787941217422485,
            "v": 2.0
        },
        "middle_mcp": {
            "x": 0.477448046207428,
            "y": 0.5695019960403442,
            "v": 2.0
        },
        "middle_pip": {
            "x": 0.47646981477737427,
            "y": 0.48266124725341797,
            "v": 2.0
        },
        "middle_dip": {
            "x": 0.4754926562309265,
            "y": 0.42222321033477783,
            "v": 2.0
        },
        "middle_tip": {
            "x": 0.473614364862442,
            "y": 0.3735327422618866,
            "v": 2.0
        },
        "ring_mcp": {
            "x": 0.4473349452018738,
            "y": 0.5732474327087402,
            "v": 2.0
        },
        "ring_pip": {
            "x": 0.4463486075401306,
            "y": 0.4889574348926544,
            "v": 2.0
        },
        "ring_dip": {
            "x": 0.4474094808101654,
            "y": 0.43337589502334595,
            "v": 2.0
        },
        "ring_tip": {
            "x": 0.4469910264015198,
            "y": 0.38816970586776733,
            "v": 2.0
        },
        "pinky_mcp": {
            "x": 0.41475939750671387,
            "y": 0.5916392207145691,
            "v": 2.0
        },
        "pinky_pip": {
            "x": 0.4122150242328644,
            "y": 0.5234939455986023,
            "v": 2.0
        },
        "pinky_dip": {
            "x": 0.41227877140045166,
            "y": 0.4804277718067169,
            "v": 2.0
        },
        "pinky_tip": {
            "x": 0.4127090871334076,
            "y": 0.4439117908477783,
            "v": 2.0
        }
    }
}