{
    "class_id": 0,
    "bbox": {
        "center_x": 0.39285714285714285,
        "center_y": 0.39732142857142855,
        "width": 0.2857142857142857,
        "height": 0.625
    },
    "keypoints": {
        "wrist": {
            "x": 0.29497456550598145,
            "y": 0.3142344057559967,
            "v": 2.0
        },
        "thumb_cmc": {
            "x": 0.3160526752471924,
            "y": 0.4037397503852844,
            "v": 2.0
        },
        "thumb_mcp": {
            "x": 0.3814278841018677,
            "y": 0.48883965611457825,
            "v": 2.0
        },
        "thumb_ip": {
            "x": 0.4169740676879883,
            "y": 0.5788112878799438,
            "v": 2.0
        },
        "thumb_tip": {
            "x": 0.43830108642578125,
            "y": 0.6663457751274109,
            "v": 2.0
        },
        "index_mcp": {
            "x": 0.4953003227710724,
            "y": 0.3671787977218628,
            "v": 2.0
        },
        "index_pip": {
            "x": 0.41057080030441284,
            "y": 0.3924257755279541,
            "v": 2.0
        },
        "index_dip": {
            "x": 0.3567112684249878,
            "y": 0.4034610092639923,
            "v": 2.0
        },
        "index_tip": {
            "x": 0.3708805441856384,
            "y": 0.39637166261672974,
            "v": 2.0
        },
        "middle_mcp": {
            "x": 0.48900705575942993,
            "y": 0.27491453289985657,
            "v": 2.0
        },
        "middle_pip": {
            "x": 0.3700413703918457,
            "y": 0.2977384328842163,
            "v": 2.0
        },
        "middle_dip": {
            "x": 0.3270571827888489,
            "y": 0.3222147822380066,
            "v": 2.0
        },
        "middle_tip": {
            "x": 0.35296952724456787,
            "y": 0.31746307015419006,
            "v": 2.0
        },
        "ring_mcp": {
            "x": 0.45624470710754395,
            "y": 0.2002566158771515,
            "v": 2.0
        },
        "ring_pip": {
            "x": 0.3482082188129425,
            "y": 0.2161523699760437,
            "v": 2.0
        },
        "ring_dip": {
            "x": 0.3146132826805115,
            "y": 0.24486678838729858,
            "v": 2.0
        },
        "ring_tip": {
            "x": 0.3477281332015991,
            "y": 0.24641147255897522,
            "v": 2.0
        },
        "pinky_mcp": {
            "x": 0.4149053394794464,
            "y": 0.1380867063999176,
            "v": 2.0
        },
        "pinky_pip": {
            "x": 0.344687283039093,
            "y": 0.1298435628414154,
            "v": 2.0
        },
        "pinky_dip": {
            "x": 0.3158252239227295,
            "y": 0.15621094405651093,
            "v": 2.0
        },
        "pinky_tip": {
            "x": 0.3274272084236145,
            "y": 0.17000243067741394,
            "v": 2.0
        }
    }
}