{
    "class_id": 0,
    "bbox": {
        "center_x": 0.39732142857142855,
        "center_y": 0.37723214285714285,
        "width": 0.6875,
        "height": 0.7544642857142857
    },
    "keypoints": {
        "wrist": {
            "x": 0.0,
            "y": 0.0,
            "v": 0.0
        },
        "thumb_cmc": {
            "x": 0.0,
            "y": 0.0,
            "v": 0.0
        },
        "thumb_mcp": {
            "x": 0.23822832107543945,
            "y": 0.05700576305389404,
            "v": 2.0
        },
        "thumb_ip": {
            "x": 0.16079720854759216,
            "y": 0.1631738394498825,
            "v": 2.0
        },
        "thumb_tip": {
            "x": 0.09852376580238342,
            "y": 0.2586694061756134,
            "v": 2.0
        },
        "index_mcp": {
            "x": 0.3271684944629669,
            "y": 0.24965950846672058,
            "v": 2.0
        },
        "index_pip": {
            "x": 0.29901352524757385,
            "y": 0.4402306079864502,
            "v": 2.0
        },
        "index_dip": {
            "x": 0.28762391209602356,
            "y": 0.5541625618934631,
            "v": 2.0
        },
        "index_tip": {
            "x": 0.28188687562942505,
            "y": 0.6440989375114441,
            "v": 2.0
        },
        "middle_mcp": {
            "x": 0.4359104633331299,
            "y": 0.2740497589111328,
            "v": 2.0
        },
        "middle_pip": {
            "x": 0.41221335530281067,
            "y": 0.4763415455818176,
            "v": 2.0
        },
        "middle_dip": {
            "x": 0.400065541267395,
            "y": 0.6100912094116211,
            "v": 2.0
        },
        "middle_tip": {
            "x": 0.39204245805740356,
            "y": 0.7136279940605164,
            "v": 2.0
        },
        "ring_mcp": {
            "x": 0.5407742857933044,
            "y": 0.26387155055999756,
            "v": 2.0
        },
        "ring_pip": {
            "x": 0.5440360307693481,
            "y": 0.4579175114631653,
            "v": 2.0
        },
        "ring_dip": {
            "x": 0.554657518863678,
            "y": 0.5829764604568481,
            "v": 2.0
        },
        "ring_tip": {
            "x": 0.5599929094314575,
            "y": 0.6793761253356934,
            "v": 2.0
        },
        "pinky_mcp": {
            "x": 0.6265173554420471,
            "y": 0.22616857290267944,
            "v": 2.0
        },
        "pinky_pip": {
            "x": 0.6539713740348816,
            "y": 0.3734379708766937,
            "v": 2.0
        },
        "pinky_dip": {
            "x": 0.6791448593139648,
            "y": 0.46209436655044556,
            "v": 2.0
        },
        "pinky_tip": {
            "x": 0.696776270866394,
            "y": 0.5400988459587097,
            "v": 2.0
        }
    }
}