{
    "class_id": 0,
    "bbox": {
        "center_x": 0.2767857142857143,
        "center_y": 0.5357142857142857,
        "width": 0.23214285714285715,
        "height": 0.41964285714285715
    },
    "keypoints": {
        "wrist": {
            "x": 0.3502764105796814,
            "y": 0.6525365710258484,
            "v": 2.0
        },
        "thumb_cmc": {
            "x": 0.3458613455295563,
            "y": 0.5817818641662598,
            "v": 2.0
        },
        "thumb_mcp": {
            "x": 0.33125630021095276,
            "y": 0.5022122263908386,
            "v": 2.0
        },
        "thumb_ip": {
            "x": 0.32729554176330566,
            "y": 0.4408901035785675,
            "v": 2.0
        },
        "thumb_tip": {
            "x": 0.33077362179756165,
            "y": 0.39468204975128174,
            "v": 2.0
        },
        "index_mcp": {
            "x": 0.29949650168418884,
            "y": 0.5085764527320862,
            "v": 2.0
        },
        "index_pip": {
            "x": 0.27555665373802185,
            "y": 0.44542837142944336,
            "v": 2.0
        },
        "index_dip": {
            "x": 0.25969693064689636,
            "y": 0.4063008427619934,
            "v": 2.0
        },
        "index_tip": {
            "x": 0.25011345744132996,
            "y": 0.3716147541999817,
            "v": 2.0
        },
        "middle_mcp": {
            "x": 0.28533613681793213,
            "y": 0.5597612857818604,
            "v": 2.0
        },
        "middle_pip": {
            "x": 0.24733713269233704,
            "y": 0.5431020259857178,
            "v": 2.0
        },
        "middle_dip": {
            "x": 0.2242584377527237,
            "y": 0.538631021976471,
            "v": 2.0
        },
        "middle_tip": {
            "x": 0.20692336559295654,
            "y": 0.5340952277183533,
            "v": 2.0
        },
        "ring_mcp": {
            "x": 0.2796500623226166,
            "y": 0.6218593120574951,
            "v": 2.0
        },
        "ring_pip": {
            "x": 0.2436468005180359,
            "y": 0.6229069828987122,
            "v": 2.0
        },
        "ring_dip": {
            "x": 0.22672274708747864,
            "y": 0.6210886836051941,
            "v": 2.0
        },
        "ring_tip": {
            "x": 0.21317331492900848,
            "y": 0.6149813532829285,
            "v": 2.0
        },
        "pinky_mcp": {
            "x": 0.2806174159049988,
            "y": 0.6850476861000061,
            "v": 2.0
        },
        "pinky_pip": {
            "x": 0.2570442259311676,
            "y": 0.7034336924552917,
            "v": 2.0
        },
        "pinky_dip": {
            "x": 0.2509928345680237,
            "y": 0.7051957845687866,
            "v": 2.0
        },
        "pinky_tip": {
            "x": 0.24596050381660461,
            "y": 0.7001604437828064,
            "v": 2.0
        }
    }
}