{
    "class_id": 0,
    "bbox": {
        "center_x": 0.7566964285714286,
        "center_y": 0.33482142857142855,
        "width": 0.14732142857142858,
        "height": 0.41964285714285715
    },
    "keypoints": {
        "wrist": {
            "x": 0.7283157110214233,
            "y": 0.502159833908081,
            "v": 2.0
        },
        "thumb_cmc": {
            "x": 0.7303791046142578,
            "y": 0.44324785470962524,
            "v": 2.0
        },
        "thumb_mcp": {
            "x": 0.7441611289978027,
            "y": 0.3775564730167389,
            "v": 2.0
        },
        "thumb_ip": {
            "x": 0.756860613822937,
            "y": 0.33156436681747437,
            "v": 2.0
        },
        "thumb_tip": {
            "x": 0.7652912735939026,
            "y": 0.2938743233680725,
            "v": 2.0
        },
        "index_mcp": {
            "x": 0.7536642551422119,
            "y": 0.3467633128166199,
            "v": 2.0
        },
        "index_pip": {
            "x": 0.7671068906784058,
            "y": 0.2773151099681854,
            "v": 2.0
        },
        "index_dip": {
            "x": 0.7744430303573608,
            "y": 0.2249942421913147,
            "v": 2.0
        },
        "index_tip": {
            "x": 0.7806586027145386,
            "y": 0.1830846220254898,
            "v": 2.0
        },
        "middle_mcp": {
            "x": 0.7553579211235046,
            "y": 0.3501346707344055,
            "v": 2.0
        },
        "middle_pip": {
            "x": 0.7699005603790283,
            "y": 0.27463001012802124,
            "v": 2.0
        },
        "middle_dip": {
            "x": 0.779342532157898,
            "y": 0.21900807321071625,
            "v": 2.0
        },
        "middle_tip": {
            "x": 0.7869954705238342,
            "y": 0.17022685706615448,
            "v": 2.0
        },
        "ring_mcp": {
            "x": 0.7562768459320068,
            "y": 0.3597918152809143,
            "v": 2.0
        },
        "ring_pip": {
            "x": 0.7715631127357483,
            "y": 0.28756844997406006,
            "v": 2.0
        },
        "ring_dip": {
            "x": 0.7814315557479858,
            "y": 0.23823139071464539,
            "v": 2.0
        },
        "ring_tip": {
            "x": 0.7879027724266052,
            "y": 0.1946984976530075,
            "v": 2.0
        },
        "pinky_mcp": {
            "x": 0.7591930031776428,
            "y": 0.37551864981651306,
            "v": 2.0
        },
        "pinky_pip": {
            "x": 0.7712166905403137,
            "y": 0.3288043737411499,
            "v": 2.0
        },
        "pinky_dip": {
            "x": 0.7769802808761597,
            "y": 0.29587727785110474,
            "v": 2.0
        },
        "pinky_tip": {
            "x": 0.7812653183937073,
            "y": 0.2661699056625366,
            "v": 2.0
        }
    }
}