{
    "class_id": 0,
    "bbox": {
        "center_x": 0.5535714285714286,
        "center_y": 0.4419642857142857,
        "width": 0.25892857142857145,
        "height": 0.38392857142857145
    },
    "keypoints": {
        "wrist": {
            "x": 0.4730202555656433,
            "y": 0.4195489287376404,
            "v": 2.0
        },
        "thumb_cmc": {
            "x": 0.5000460147857666,
            "y": 0.4612698256969452,
            "v": 2.0
        },
        "thumb_mcp": {
            "x": 0.538019597530365,
            "y": 0.5049819946289062,
            "v": 2.0
        },
        "thumb_ip": {
            "x": 0.5569074153900146,
            "y": 0.550338625907898,
            "v": 2.0
        },
        "thumb_tip": {
            "x": 0.5646953582763672,
            "y": 0.5927685499191284,
            "v": 2.0
        },
        "index_mcp": {
            "x": 0.6410080790519714,
            "y": 0.43627575039863586,
            "v": 2.0
        },
        "index_pip": {
            "x": 0.6145275831222534,
            "y": 0.4527815878391266,
            "v": 2.0
        },
        "index_dip": {
            "x": 0.5724478363990784,
            "y": 0.46140429377555847,
            "v": 2.0
        },
        "index_tip": {
            "x": 0.5673534870147705,
            "y": 0.45853540301322937,
            "v": 2.0
        },
        "middle_mcp": {
            "x": 0.6333187818527222,
            "y": 0.38351649045944214,
            "v": 2.0
        },
        "middle_pip": {
            "x": 0.5933637022972107,
            "y": 0.4036545157432556,
            "v": 2.0
        },
        "middle_dip": {
            "x": 0.5475909113883972,
            "y": 0.42305123805999756,
            "v": 2.0
        },
        "middle_tip": {
            "x": 0.546035647392273,
            "y": 0.425545334815979,
            "v": 2.0
        },
        "ring_mcp": {
            "x": 0.6088657379150391,
            "y": 0.33734843134880066,
            "v": 2.0
        },
        "ring_pip": {
            "x": 0.5739513039588928,
            "y": 0.3541984558105469,
            "v": 2.0
        },
        "ring_dip": {
            "x": 0.5323376059532166,
            "y": 0.38013797998428345,
            "v": 2.0
        },
        "ring_tip": {
            "x": 0.5305095314979553,
            "y": 0.38867801427841187,
            "v": 2.0
        },
        "pinky_mcp": {
            "x": 0.5790205001831055,
            "y": 0.29795366525650024,
            "v": 2.0
        },
        "pinky_pip": {
            "x": 0.563449501991272,
            "y": 0.2989637553691864,
            "v": 2.0
        },
        "pinky_dip": {
            "x": 0.5326407551765442,
            "y": 0.32093074917793274,
            "v": 2.0
        },
        "pinky_tip": {
            "x": 0.52558434009552,
            "y": 0.33299562335014343,
            "v": 2.0
        }
    }
}